recipe_manager/__init__.py
recipe_manager/components/__init__.py
recipe_manager/components/ingredients.py
recipe_manager/components/recipe.py
recipe_manager/metrics/__init__.py
recipe_manager/metrics/conversions.py
recipe_manager/metrics/nutrition.py
recipe_manager_montwh1te-0.0.1.dist-info/METADATA
recipe_manager_montwh1te-0.0.1.dist-info/WHEEL
recipe_manager_montwh1te-0.0.1.dist-info/top_level.txt
recipe_manager_montwh1te-0.0.1.dist-info/RECORD
