Metadata-Version: 2.1
Name: recipe_manager_montwh1te
Version: 0.0.1
Summary: a package that can improve your recipe and baking management
Home-page: https://github.com/montwh1te/recipe-package-template.git
Author: montwh1te
Author-email: eduardomatuella@gmail.com
Requires-Python: >= 3.8
Requires-Dist: noms
Requires-Dist: unitconvert
